{
    "@class": "com.kony.gen.viz.model.container.KVizScrollFlexForm",
    "DNDConfig": null,
    "_margin_": [
        0,
        0,
        0,
        0
    ],
    "_padding_": [
        0,
        0,
        0,
        0
    ],
    "_skin_": "s5be5703e391477388d0320904d06b21",
    "_title_": null,
    "addWidgetsdone": false,
    "allboxes": [],
    "canUpdateUI": true,
    "children": [
        "flxcRoot"
    ],
    "containerId": true,
    "containerWeight": 100,
    "containerweight": 100,
    "contentOffsetX": 0,
    "contentOffsetY": 0,
    "contentSizeHeight": 0,
    "contentSizeWidth": 0,
    "currentLocale": null,
    "device": "iPhone6",
    "displayOrientation": 3,
    "displayorientation": 3,
    "enabled": false,
    "enabledForIdleTimeout": false,
    "enabledforidletimeout": false,
    "id": "tmplComics",
    "inTransitionConfig": {
        "formTransition": "None"
    },
    "info": null,
    "initdone": false,
    "inputAccessoryViewType": 4,
    "inputaccessoryviewtype": 4,
    "intransitionconfig": {
        "formTransition": "None"
    },
    "isVisible": true,
    "isvisible": true,
    "kuid": "d093a7f9dd744d56abf53494b1667034",
    "margin": [
        0,
        0,
        0,
        0
    ],
    "name": "kony.ui.Form2",
    "needAppMenu": true,
    "needappmenu": true,
    "orientation": 1,
    "outTransitionConfig": {
        "formTransition": "None"
    },
    "outtransitionconfig": {
        "formTransition": "None"
    },
    "padding": [
        0,
        0,
        0,
        0
    ],
    "paddingInPixel": false,
    "paddinginpixel": false,
    "percent": true,
    "platform": "iphone",
    "prevDevice": "iPhone6",
    "prevPlatform": "iphone",
    "render": true,
    "retainScrollPosition": false,
    "retainscrollposition": false,
    "shellCSS": "iOS_iPhone6",
    "skin": "s5be5703e391477388d0320904d06b21",
    "title": null,
    "titleBar": true,
    "titleBarSkin": "s945d393a8264546aea99bbde2956bbe",
    "titlebar": true,
    "type": 3,
    "wType": "Form",
    "widgetAlignment": 5
}